pulp_glue/ansible/__init__.py
pulp_glue/ansible/context.py
pulp_glue/ansible/py.typed
pulp_glue/ansible/locale/de/LC_MESSAGES/messages.mo
pulp_glue/certguard/__init__.py
pulp_glue/certguard/context.py
pulp_glue/certguard/py.typed
pulp_glue/certguard/locale/de/LC_MESSAGES/messages.mo
pulp_glue/common/__init__.py
pulp_glue/common/authentication.py
pulp_glue/common/context.py
pulp_glue/common/exceptions.py
pulp_glue/common/i18n.py
pulp_glue/common/openapi.py
pulp_glue/common/py.typed
pulp_glue/common/schema.py
pulp_glue/common/locale/de/LC_MESSAGES/messages.mo
pulp_glue/container/__init__.py
pulp_glue/container/context.py
pulp_glue/container/py.typed
pulp_glue/container/locale/de/LC_MESSAGES/messages.mo
pulp_glue/core/__init__.py
pulp_glue/core/context.py
pulp_glue/core/py.typed
pulp_glue/core/locale/de/LC_MESSAGES/messages.mo
pulp_glue/file/__init__.py
pulp_glue/file/context.py
pulp_glue/file/py.typed
pulp_glue/file/locale/de/LC_MESSAGES/messages.mo
pulp_glue/python/__init__.py
pulp_glue/python/context.py
pulp_glue/python/py.typed
pulp_glue/python/locale/de/LC_MESSAGES/messages.mo
pulp_glue/rpm/__init__.py
pulp_glue/rpm/context.py
pulp_glue/rpm/py.typed
pulp_glue/rpm/locale/de/LC_MESSAGES/messages.mo
pulp_glue-0.37.0.dist-info/METADATA
pulp_glue-0.37.0.dist-info/WHEEL
pulp_glue-0.37.0.dist-info/top_level.txt
pulp_glue-0.37.0.dist-info/RECORD
